{
  "user_id": "12f3baa5-03ea-40d7-940e-783268db81fb",
  "timestamp": "2025-11-08T10:23:17.876116",
  "assigned_personas": [
    "high_utilization"
  ],
  "primary_persona": "high_utilization",
  "matching_results": {
    "high_utilization": {
      "matched": true,
      "matched_criteria": 1,
      "total_criteria": 5,
      "score": 1,
      "reasons": [
        "Criterion 4: Making only minimum payments"
      ],
      "risk": 5,
      "risk_level": "CRITICAL",
      "points_per_criterion": 1.25,
      "total_points": 1.25
    },
    "variable_income_budgeter": {
      "matched": false,
      "matched_criteria": 0,
      "total_criteria": 5,
      "score": 0,
      "reasons": [],
      "risk": 4,
      "risk_level": "HIGH",
      "points_per_criterion": 1.0,
      "total_points": 0.0
    },
    "subscription_heavy": {
      "matched": false,
      "matched_criteria": 0,
      "total_criteria": 5,
      "score": 0,
      "reasons": [],
      "risk": 3,
      "risk_level": "MEDIUM",
      "points_per_criterion": 0.75,
      "total_points": 0.0
    },
    "savings_builder": {
      "matched": false,
      "matched_criteria": 0,
      "total_criteria": 5,
      "score": 0,
      "reasons": [],
      "risk": 2,
      "risk_level": "LOW",
      "points_per_criterion": 0.25,
      "total_points": 0.0
    },
    "fee_accumulator": {
      "matched": false,
      "matched_criteria": 0,
      "total_criteria": 5,
      "score": 0,
      "reasons": [],
      "risk": 3,
      "risk_level": "MEDIUM",
      "points_per_criterion": 0.85,
      "total_points": 0.0
    }
  },
  "features_snapshot": {
    "user_id": "12f3baa5-03ea-40d7-940e-783268db81fb",
    "window_days": 180,
    "start_date": "2025-05-12T10:23:16.367095",
    "end_date": "2025-11-08T10:23:16.367095",
    "subscriptions": {
      "recurring_merchants": 3,
      "recurring_merchant_details": [
        {
          "merchant_name": "HBO Max",
          "occurrences": 6,
          "cadence": "monthly",
          "average_interval_days": 30.0,
          "total_amount": 78.5051300731392,
          "average_amount": 13.0841883455232,
          "first_transaction": "2025-06-07 16:08:58.465132",
          "last_transaction": "2025-11-04 16:08:58.465132"
        },
        {
          "merchant_name": "Delta Airlines",
          "occurrences": 5,
          "cadence": "monthly",
          "average_interval_days": 31.25,
          "total_amount": 188.2379185659101,
          "average_amount": 37.647583713182016,
          "first_transaction": "2025-06-01 06:45:16.035455",
          "last_transaction": "2025-10-07 16:31:28.528609"
        },
        {
          "merchant_name": "Trader Joe's",
          "occurrences": 4,
          "cadence": "monthly",
          "average_interval_days": 32.666666666666664,
          "total_amount": 47.86667905372703,
          "average_amount": 11.966669763431758,
          "first_transaction": "2025-07-12 14:07:44.256825",
          "last_transaction": "2025-10-19 08:01:36.228984"
        }
      ],
      "monthly_recurring_spend": 62.69844182213698,
      "average_subscription_cost": 20.899480607378994,
      "total_subscription_spend": 314.6097276927763,
      "subscription_share_of_total": 2.5739528444154147,
      "subscription_to_income_ratio": 0.0,
      "subscription_categories": {
        "streaming": [
          "HBO Max"
        ]
      },
      "category_duplicates": {},
      "has_category_duplicates": false,
      "total_spend": 12222.824065148292
    },
    "savings": {
      "net_inflow": 0.0,
      "monthly_net_inflow": 0.0,
      "growth_rate_percent": 0.0,
      "emergency_fund_coverage_months": 3.654788541378457,
      "total_savings_balance": 1215.7392596390196,
      "average_monthly_expenses": 332.64284537252206,
      "has_emergency_fund": true
    },
    "credit": {
      "has_credit_cards": true,
      "total_cards": 1,
      "any_high_utilization_50": false,
      "any_high_utilization_80": false,
      "any_interest_charges": false,
      "any_minimum_payment_only": true,
      "any_overdue": false,
      "card_details": [
        {
          "account_id": "652963863960",
          "name": "Discover Credit Card",
          "utilization": {
            "account_id": "652963863960",
            "utilization_percent": 34.601031707505605,
            "balance": 8650.257926876402,
            "limit": 25000.0,
            "available": 16349.742073123598,
            "is_high_utilization_30": true,
            "is_high_utilization_50": false,
            "is_high_utilization_80": false
          },
          "interest_charges": {
            "has_interest_charges": false,
            "total_interest_charges": 0,
            "monthly_interest_estimate": 0.0,
            "interest_transactions": 0
          },
          "minimum_payment_only": true,
          "is_overdue": false
        }
      ]
    },
    "income": {
      "has_payroll_detected": false,
      "total_payroll_transactions": 0,
      "average_income_per_pay": 0.0,
      "minimum_monthly_income": 0.0,
      "distinct_income_sources_90d": 1,
      "payment_frequency": {
        "frequency": "unknown",
        "average_days_between": 0.0,
        "median_days_between": 0.0,
        "frequency_variability": 0.0,
        "is_regular": false
      },
      "median_pay_gap_days": 0.0,
      "cash_flow_buffer_months": 6.112342282606979,
      "checking_balance": 2196.047664382908,
      "average_monthly_expenses": 359.2808718569128,
      "has_sufficient_buffer": true,
      "is_variable_income": false
    },
    "fees": {
      "overdraft_nsf_fees_90d": 0,
      "total_fees_last_month": 0.0,
      "atm_fees_90d": 0,
      "accounts_with_late_fees": 0,
      "has_maintenance_fees": false,
      "maintenance_fees_90d": 0,
      "total_fees_90d": 0,
      "overdraft_fees": 0,
      "nsf_fees": 0,
      "atm_fees": 0,
      "late_payment_fees": 0,
      "maintenance_fees": 0,
      "total_fees": 0,
      "fee_transactions": []
    }
  },
  "rationale": "Assigned to High Utilization persona (1/5 criteria matched, 100% match)."
}